uc_functions/__init__.py
uc_functions/functions.py
uc_functions/inline.py
uc_functions/special_kwargs.py
uc_functions/visitors.py
uc_functions-0.3.0.dist-info/LICENSE
uc_functions-0.3.0.dist-info/METADATA
uc_functions-0.3.0.dist-info/WHEEL
uc_functions-0.3.0.dist-info/top_level.txt
uc_functions-0.3.0.dist-info/RECORD
