Metadata-Version: 2.1
Name: uc-functions
Version: 0.3.0
Summary: Decorator to compile Python functions to Databricks UDFs sql statements and inline all the dependencies
Home-page: https://github.com/stikkireddy/uc-functions
Author: Sri Tikkireddy
Author-email: sri.tikkireddy@databricks.com
Classifier: Programming Language :: Python :: 3
Classifier: License :: OSI Approved :: Apache Software License
Classifier: Operating System :: OS Independent
Requires-Python: >=3.10
License-File: LICENSE
Requires-Dist: astor
Requires-Dist: databricks-sdk >=0.18.0
Requires-Dist: black
Requires-Dist: pyflakes
